safetybox/__init__.py
safetybox/_version.py
safetybox/cli.py
safetybox/crypto.py
safetybox/iocs.py
safetybox/logs.py
safetybox/passwords.py
safetybox/pcap.py
safetybox/plugin.py
safetybox-0.1.1.dist-info/licenses/LICENSE
safetybox-0.1.1.dist-info/METADATA
safetybox-0.1.1.dist-info/WHEEL
safetybox-0.1.1.dist-info/top_level.txt
safetybox-0.1.1.dist-info/RECORD
