Metadata-Version: 2.4
Name: safetybox
Version: 0.1.1
Summary: Secutils — defensive security & forensic utilities (passive analysis)
Author: Sakura Golden (via ChatGPT)
License: MIT
Classifier: Programming Language :: Python :: 3
Classifier: License :: OSI Approved :: MIT License
Classifier: Operating System :: OS Independent
Requires-Python: >=3.8
License-File: LICENSE
Requires-Dist: click>=8.0
Provides-Extra: pcap
Requires-Dist: scapy>=2.4.5; extra == "pcap"
Provides-Extra: crypto
Requires-Dist: cryptography>=3.4; extra == "crypto"
Provides-Extra: intel
Requires-Dist: requests>=2.28; extra == "intel"
Dynamic: license-file
